rootcause/__init__.py
rootcause/api.py
rootcause/base.py
rootcause/causes.py
rootcause/meta.py
rootcause/mysql.py
rootcause/postgres.py
rootcause/sqlite.py
rootcause-1.0.0.dist-info/WHEEL
rootcause-1.0.0.dist-info/METADATA
rootcause-1.0.0.dist-info/RECORD
