Metadata-Version: 2.3
Name: rootcause
Version: 1.0.0
Summary: Get something useful out your IntegrityErrors
Author: Kevin Wetzels
Author-email: Kevin Wetzels <kevin@roam.be>
Classifier: Development Status :: 5 - Production/Stable
Classifier: Framework :: Django :: 5.2
Classifier: Framework :: Django :: 6.0
Classifier: Intended Audience :: Developers
Classifier: Natural Language :: English
Classifier: Operating System :: OS Independent
Classifier: Programming Language :: Python :: 3 :: Only
Classifier: License :: OSI Approved :: BSD License
Classifier: Programming Language :: Python :: 3.10
Classifier: Programming Language :: Python :: 3.11
Classifier: Programming Language :: Python :: 3.12
Classifier: Programming Language :: Python :: 3.13
Classifier: Programming Language :: Python :: 3.14
Classifier: Programming Language :: Python :: Implementation :: CPython
Requires-Dist: django
Maintainer: Kevin Wetzels
Maintainer-email: Kevin Wetzels <kevin@roam.be>
Requires-Python: >=3.10
Project-URL: Changelog, https://github.com/roam/rootcause/blob/main/CHANGELOG.md
Project-URL: Documentation, https://github.com/roam/rootcause/blob/main/README.md
Project-URL: Homepage, https://github.com/roam/rootcause/
Project-URL: Issues, https://github.com/roam/rootcause/issues
Project-URL: Repository, https://github.com/roam/rootcause.git
